declara/Declaratieformulier_v3F.pdf
declara/__init__.py
declara/default_email_body.txt
declara-1.0.4.data/data/Declaratieformulier_v3F.pdf
declara-1.0.4.data/data/__init__.py
declara-1.0.4.data/data/default_email_body.txt
declara-1.0.4.dist-info/LICENSE
declara-1.0.4.dist-info/WHEEL
declara-1.0.4.dist-info/METADATA
declara-1.0.4.dist-info/RECORD
