Metadata-Version: 2.1
Name: declara
Version: 1.0.4
Summary: Declara, a library for generating Boreas declaration forms
Author-email: Tobias Sijtsma <tobias@leanslate.nl>
Requires-Python: >=3.10
Requires-Dist: pypdf2 >=2.11, <3
Requires-Dist: reportlab >=3.6, <4
Requires-Dist: requests >=2.28, <3
Requires-Dist: yagmail[all] >=0.15, <1
Project-URL: Home, https://leanslate.nl/
Project-URL: source, https://github.com/Tobiaqs/declara
